{
  "treinamento": "MAQUIAGEM NO AMBIENTE CORPORATIVO_PADRÃO DE ATENDIMENTO PARA RECEPÇÃO",
  "id": 1048,
  "idChecklist": 822,
  "perguntas": [
    {
      "pergunta": "5) QUAL É A RECOMENDAÇÃO RELACIONADA AOS CUIDADOS DIÁRIOS COM A PELE DEPOIS DO USO DA MAQUIAGEM?",
      "opcoes": [
        "DEIXAR A MAQUIAGEM DURANTE A NOITE PARA ECONOMIZAR TEMPO.",
        "RETIRAR DIARIAMENTE A MAQUIAGEM PARA MANTER A PELE BRILHOSA.",
        "REAPLICAR OS PRODUTOS PARA GARANTIR UMA APARÊNCIA CONSISTENTE.",
        "RETIRAR DIARIAMENTE A MAQUIAGEM PARA MANTER A PELE SAUDÁVEL."
      ]
    },
    {
      "pergunta": "4) QUAIS EXCESSOS DEVEMOS EVITAR NA MAQUIAGEM?",
      "opcoes": [
        "CORES CHAMATIVAS, BRILHO, UNHAS EXTRAVAGANTES E APLICAÇÃO PESADA DE PRODUTOS.",
        "CORES NEUTRAS, BRILHO, UNHAS DISCRETAS E APLICAÇÃO PESADA DE PRODUTOS.",
        "CORES CHAMATIVAS, BRILHO, UNHAS EXTRAVAGANTES E APLICAÇÃO LEVE DE PRODUTOS.",
        "NENHUMA DAS ALTERNATIVAS ANTERIORES."
      ]
    },
    {
      "pergunta": "3) QUAL É A RECOMENDAÇÃO DE APLICAÇÃO DE PRODUTOS PARA OS LÁBIOS NO AMBIENTE DE TRABALHO?",
      "opcoes": [
        "BATONS COM CORES VIBRANTES E BRILHOS INTENSOS.",
        "OPTAR POR TONS DISCRETOS E FOSCOS.",
        "USAR CORES VARIADAS PARA COMPLEMENTAR A APARÊNCIA.",
        "UTILIZAR SOMENTE GLOSS PARA UM ASPECTO NATURAL."
      ]
    },
    {
      "pergunta": "2) O QUE É ENFATIZADO COMO FUNDAMENTAL PARA OS OLHOS NA MAQUIAGEM CORPORATIVA?",
      "opcoes": [
        "SOMBRAS CHAMATIVAS E DELINEADORES EXTRAVAGANTES.",
        "TONS NEUTROS E APLICAÇÃO MODERADA.",
        "CORES BRILHANTES PARA DESTACAR O OLHAR.",
        "EXAGERO NA APLICAÇÃO PARA EXPRESSIVIDADE."
      ]
    },
    {
      "pergunta": "1) QUAL É O PRINCIPAL OBJETIVO DA MAQUIAGEM NO AMBIENTE CORPORATIVO DE ACORDO COM O TREINAMENTO?",
      "opcoes": [
        "CHAMAR A ATENÇÃO PARA CARACTERÍSTICAS FACIAIS ESPECÍFICAS.",
        "DESTACAR-SE COM CORES VIBRANTES E EXPRESSIVAS.",
        "REALÇAR A AUTOCONFIANÇA E TRANSMITIR UMA IMAGEM PROFISSIONAL.",
        "MANTER UMA APARÊNCIA FESTIVA E DIVERTIDA."
      ]
    }
  ]
}