{
  "treinamento": "PRINCIPAIS ERROS DE PORTUGUÊS A SEREM EVITADOS",
  "id": 1052,
  "idChecklist": 826,
  "perguntas": [
    {
      "pergunta": "5) O QUE SÃO CONSIDERADOS VÍCIOS DE LINGUAGEM, DE ACORDO COM AS NORMAS GRAMATICAIS?",
      "opcoes": [
        "A) EXPRESSÕES POPULARES.",
        "B) CONSTRUÇÕES MAL-EMPREGADAS.",
        "C) GÍRIAS E REGIONALISMOS.",
        "D) TERMOS TÉCNICOS."
      ]
    },
    {
      "pergunta": "4) QUAL É A PRINCIPAL DESVANTAGEM APONTADA QUANDO HÁ O USO DE GÍRIAS NA COMUNICAÇÃO?",
      "opcoes": [
        "A) FORTALECEM A MENSAGEM.",
        "B) TORNAM A COMUNICAÇÃO MAIS ASSERTIVA.",
        "C) ENFRAQUECEM A MENSAGEM.",
        "D) FACILITAM A COMPREENSÃO."
      ]
    },
    {
      "pergunta": "3) QUAL ALTERNATIVA PODE SER UTILIZADA PARA ELIMINAR GÍRIAS E EXPRESSÕES COMO \"NÉ\" NA COMUNICAÇÃO?",
      "opcoes": [
        "A) AUMENTAR O USO DE GÍRIAS.",
        "B) UTILIZAR PAUSAS.",
        "C) INTRODUZIR MAIS EXPRESSÕES INFORMAIS.",
        "D) ADOTAR UM TOM MAIS COLOQUIAL."
      ]
    },
    {
      "pergunta": "2) QUAL É O EXEMPLO DE EXPRESSÃO ABAIXO CARACTERIZA O PLEONASMO?",
      "opcoes": [
        "A) \"TELEFONAREI ASSIM QUE A ENCOMENDA CHEGAR\".",
        "B) \"ESTE FILME É BASEADO EM FATOS REAIS\".",
        "C) \"SUBIR PRA CIMA\".",
        "D) \"NÓS VAI\"."
      ]
    },
    {
      "pergunta": "1) QUAL É O TERMO UTILIZADO PARA SE REFERIR À REPETIÇÃO DE UMA IDEIA QUE JÁ SE EXPLICA SOZINHA, COMO \"SUBIR PRA CIMA\" OU \"DESCER PRA BAIXO\"?",
      "opcoes": [
        "A) PLEONASMO.",
        "B) GERUNDISMO.",
        "C) GÍRIA.",
        "D) VÍCIO DE LINGUAGEM."
      ]
    }
  ]
}