{
  "treinamento": "FUNCIONALIDADES DO PORTAL GPS360",
  "id": 1252,
  "idChecklist": 1018,
  "perguntas": [
    {
      "pergunta": "5)  O QUE O MENU \"CONHECENDO O GPS360\" OFERECE AOS CLIENTES?",
      "opcoes": [
        "EXCLUSÃO DE TAREFAS.",
        "NÃO FAZER UMA APRESENTAÇÃO TESTE.",
        "ACESSO AO SUPORTE TÉCNICO DO TIME GPS360.",
        "DICAS SOBRE O USO DOS FILTROS, INFORMAÇÕES SOBRE OS RELATÓRIOS E DINÂMICAS PARA FACILITAR O DIA A DIA."
      ]
    },
    {
      "pergunta": "4) QUAL MENU NO PORTAL GPS360 FACILITA O DOWNLOAD DE DOCUMENTOS RELACIONADOS AO CONTRATO?",
      "opcoes": [
        "PERFORMANCE CONTRATUAL.",
        "DOWNLOAD.",
        "MOVIMENTAÇÃO PESSOAL.",
        "SUPORTE VIA E-MAIL."
      ]
    },
    {
      "pergunta": "3) ATRAVÉS DO MENU \"DOCUMENTAÇÃO SOLIDÁRIA\" QUAIS INFORMAÇÕES O USUÁRIO PODE ACOMPANHAR?",
      "opcoes": [
        "TODOS OS DOCUMENTOS RELACIONADOS ÀS OBRIGAÇÕES ACESSÓRIAS DA EMPRESA CONFORME O CRONOGRAMA.",
        "RESULTADOS FINANCEIROS DOS CONTRATOS.",
        "MOVIMENTAÇÕES PESSOAIS COMO ADMISSÕES E RESCISÕES.",
        "ACOMPANHAMENTO DOS RELATÓRIOS DE TREINAMENTO E PAGAMENTO."
      ]
    },
    {
      "pergunta": "2) QUAL É A PRINCIPAL FUNÇÃO DO MENU \"PERFORMANCE CONTRATUAL\" NO PORTAL GPS360?",
      "opcoes": [
        "DOWNLOAD DOS DOCUMENTOS REFERENTES À FOLHA DE PONTO E CONTRATOS.",
        "APOIAR NA UTILIZAÇÃO DA PLATAFORMA GPS360.",
        "APRESENTAR OS RESULTADOS DO CONTRATO PARA O SEU CLIENTE ATRAVÉS DE INDICADORES, PONTOS DE ATENÇÃO, DESTAQUES E COMPROMISSOS ASSUMIDOS.",
        "APENAS AVALIAÇÃO DO CLIENTE."
      ]
    },
    {
      "pergunta": "1) QUAL É A PRINCIPAL FUNÇÃO DO MENU \"RELATÓRIOS\" NO PORTAL GPS360?",
      "opcoes": [
        "FAZER EXCLUSÃO DE DOCUMENTOS.",
        "VISUALIZAR E ANALISAR OS RELATÓRIOS DE FOLHA DE PAGAMENTO, EFETIVO ATIVO, FÉRIAS, RESCISÕES E ENTRE OUTROS.",
        "ACOMPANHAR AS INCLUSÕES DE TAREFAS.",
        "ACESSOS ÀS INFORMAÇÕES DE TODOS OS CONTRATOS."
      ]
    }
  ]
}