{
  "treinamento": "ATENDIMENTO DE OCORRÊNCIAS - MÓD II_CSE",
  "id": 1350,
  "idChecklist": 1108,
  "perguntas": [
    {
      "pergunta": "5) O QUE O ATENDENTE DEVE FAZER AO PERCEBER QUE ALGUM EQUIPAMENTO DE SEGURANÇA ESTÁ DANIFICADO?",
      "opcoes": [
        "INFORMAR A SUPERVISÃO PARA QUE O EQUIPAMENTO SEJA SUBSTITUÍDO.",
        "IGNORAR O PROBLEMA E CONTINUAR UTILIZANDO O EQUIPAMENTO.",
        "CONSERTAR O EQUIPAMENTO POR CONTA PRÓPRIA.",
        "GUARDAR O EQUIPAMENTO ATÉ QUE POSSA SER REPARADO EM OUTRA OCASIÃO"
      ]
    },
    {
      "pergunta": "4) QUAL DAS OPÇÕES ABAIXO É UMA ATITUDE INADEQUADA DURANTE O ATENDIMENTO A CLIENTES?",
      "opcoes": [
        "DEMONSTRAR RESPEITO E MANTER UMA COMUNICAÇÃO FORMAL.",
        "MANTER INTIMIDADE COMO ABRAÇOS, PRESENTES OU OFERECER CARONAS.",
        "IDENTIFICAR-SE AO CLIENTE DE FORMA PROFISSIONAL.",
        "SOLICITAR APOIO DA CENTRAL, SE NECESSÁRIO, DURANTE O ATENDIMENTO."
      ]
    },
    {
      "pergunta": "3) QUAL É O PROCEDIMENTO CORRETO EM RELAÇÃO AO USO DO CELULAR DURANTE O EXPEDIENTE?",
      "opcoes": [
        "USAR O CELULAR PESSOAL E O CORPORATIVO PARA FACILITAR A COMUNICAÇÃO.",
        "UTILIZAR O CELULAR PESSOAL DURANTE ATENDIMENTOS COM AUTORIZAÇÃO DA SUPERVISÃO.",
        "UTILIZAR APENAS O CELULAR CORPORATIVO FORNECIDO PELA EMPRESA DURANTE O EXPEDIENTE.",
        "ALTERNAR ENTRE O CELULAR PESSOAL E O CORPORATIVO DE ACORDO COM A SITUAÇÃO."
      ]
    },
    {
      "pergunta": "2) COMO O ATENDENTE DEVE REGISTRAR O PONTO DIARIAMENTE?",
      "opcoes": [
        "NO GPS APONTAMENTO, COM FOTOS NÍTIDAS E INFORMANDO A SUPERVISÃO SOBRE QUALQUER PROBLEMA.",
        "NO APLICATIVO VTR MOBILE, REGISTRANDO APENAS O HORÁRIO DE ENTRADA.",
        "NO GPS APONTAMENTO, SEM NECESSIDADE DE FOTOS.",
        "APENAS NO FINAL DO EXPEDIENTE, INFORMANDO A CENTRAL DE MONITORAMENTO."
      ]
    },
    {
      "pergunta": "1) QUAL É O COMPORTAMENTO ADEQUADO EM RELAÇÃO AO USO DO UNIFORME E AO INÍCIO DAS ATIVIDADES",
      "opcoes": [
        "INICIAR AS ATIVIDADES QUANDO ACHAR CONVENIENTE E VESTIR O UNIFORME SOMENTE QUANDO NECESSÁRIO.",
        "UTILIZAR O UNIFORME APENAS FORA DO HORÁRIO DE EXPEDIENTE.",
        "INICIAR AS ATIVIDADES SEM PARTICIPAR DA PASSAGEM DE TURNO.",
        "VESTIR O UNIFORME CORRETAMENTE E INICIAR O TRABALHO SEM ATRASOS, PARTICIPANDO DA PASSAGEM DE TURNO."
      ]
    }
  ]
}