{
  "treinamento": "PREPARAÇÕES DE RISCO - ALIMENTAÇÃO_TREINAMENTO PRESENCIAL",
  "id": 1359,
  "idChecklist": 1117,
  "perguntas": [
    {
      "pergunta": "5) DAS PREPARAÇÕES RELACIONADAS ABAIXO, QUAIS SÃO CONSIDERADAS DE RISCO E TÊM SEU PONTO CRÍTICO DE CONTROLE NO PROCESSO DE SANITIZAÇÃO?",
      "opcoes": [
        "SALADAS CRUAS E FRUTAS CRUAS.",
        "OVOS E SALADAS COZIDAS.",
        "ARROZ E FEIJÃO.",
        "FRANGO ASSADO E MACARRÃO"
      ]
    },
    {
      "pergunta": "4) DAS PREPARAÇÕES RELACIONADAS ABAIXO, QUAIS SÃO CONSIDERADAS DE RISCO E TÊM SEUS PONTOS CRÍTICOS DE CONTROLE NOS PROCESSOS DE COCÇÃO E DE RESFRIAMENTO, CONSECUTIVAMENTE?",
      "opcoes": [
        "BIFE GRELHADO E OMELETE.",
        "CARNE ASSADA E SALADA COZIDA.",
        "LASANHA E SALADA DE ALFACE.",
        "PUDIM DE BAUNILHA E FEIJÃO."
      ]
    },
    {
      "pergunta": "3) AO INCLUIR UMA PREPARAÇÃO DE RISCO NO CARDÁPIO, QUAIS FATORES DEVEM SER OBSERVADOS?",
      "opcoes": [
        "SE OS EQUIPAMENTOS DISPONÍVEIS SÃO SUFICIENTES PARA O PROCESSO DE PREPARO E ARMAZENAMENTO.",
        "SE NÃO HÁ RISCO DE CONTAMINAÇÃO CRUZADA.",
        "SE O CARDÁPIO ESTÁ ADEQUADO PARA AS CONDIÇÕES DA UNIDADE.",
        "TODAS AS ALTERNATIVAS."
      ]
    },
    {
      "pergunta": "2) QUAIS FATORES AUMENTAM O RISCO DO PERIGO BIOLÓGICO NAS PREPARAÇÕES?",
      "opcoes": [
        "TEMPERATURAS QUE TRANSITAM NA FAIXA DE RISCO (ENTRE 4°C E 65°C).",
        "MANIPULAÇÃO EXCESSIVA.",
        "DIVERSIDADE DE INGREDIENTES.",
        "TODAS AS ALTERNATIVAS ESTÃO CORRETAS."
      ]
    },
    {
      "pergunta": "1) QUAL O OBJETIVO DO PITADAS DA QUALIDADE?",
      "opcoes": [
        "CONSCIENTIZAÇÃO SOBRE MEIO AMBIENTE.",
        "TREINAMENTO SOBRE SEGURANÇA DOS ALIMENTOS.",
        "CONSCIENTIZAÇÃO SOBRE ACIDENTE E DOENÇAS DO TRABALHO.",
        "CAMPANHA SOBRE DESPERDÍCIO DE ALIMENTOS."
      ]
    }
  ]
}