{
  "treinamento": "ISPS CODE - MÓDULO I_SAMARCO",
  "id": 1445,
  "idChecklist": 1193,
  "perguntas": [
    {
      "pergunta": "5) QUEM PODE ACESSAR A ÁREA PORTUÁRIA NA SAMARCO MINERAÇÃO SA?",
      "opcoes": [
        "QUALQUER PESSOA INTERESSADA EM VISITAR O LOCAL.",
        "SOMENTE TURISTAS COM AGENDAMENTO PRÉVIO.",
        "COLABORADORES DE OUTRAS EMPRESAS SEM NECESSIDADE DE AUTORIZAÇÃO.",
        "APENAS COLABORADORES AUTORIZADOS E LIBERADOS PELO SISTEMA DE ACESSO."
      ]
    },
    {
      "pergunta": "4) QUANDO O CÓDIGO ISPS PASSOU A VIGORAR?",
      "opcoes": [
        "01/07/2004.",
        "11/09/2001.",
        "31/12/2002.",
        "20/03/2003."
      ]
    },
    {
      "pergunta": "3)  QUAL É A DIFERENÇA ENTRE O \"SAFETY SOLAS\" E O \"ISPS CODE\"?",
      "opcoes": [
        "O SAFETY SOLAS TRATA DE SEGURANÇA AMBIENTAL, ENQUANTO O ISPS CODE FOCA EM EFICIÊNCIA LOGÍSTICA.",
        "O SAFETY SOLAS É VOLTADO PARA A ECONOMIA MARÍTIMA, E O ISPS CODE PARA A PROTEÇÃO DE CARGAS.",
        "O SAFETY SOLAS TRATA DA SEGURANÇA DAS PESSOAS NO MAR, E O ISPS CODE TRATA DA PROTEÇÃO CONTRA AMEAÇAS TERRORISTAS.",
        "O SAFETY SOLAS E O ISPS CODE SÃO A MESMA COISA."
      ]
    },
    {
      "pergunta": "2) QUAL EVENTO HISTÓRICO MOTIVOU A CRIAÇÃO DO CÓDIGO ISPS?",
      "opcoes": [
        "A CRISE ECONÔMICA DE 2008.",
        "O TRATADO DE TORDESILHAS.",
        "OS ATENTADOS TERRORISTAS DO WTC EM 11/09/2001, EM NOVA YORK EUA.",
        "O ACIDENTE NUCLEAR DE CHERNOBYL."
      ]
    },
    {
      "pergunta": "1) QUAL É O PRINCIPAL OBJETIVO DO CÓDIGO ISPS?",
      "opcoes": [
        "MELHORAR A EFICIÊNCIA DO TRANSPORTE MARÍTIMO.",
        "PREVENIR A INTRODUÇÃO DE ARMAS E SUBSTÂNCIAS PERIGOSAS EM INSTALAÇÕES PORTUÁRIAS.",
        "REDUZIR OS CUSTOS OPERACIONAIS DOS PORTOS.",
        "PROMOVER O TURISMO EM ÁREAS PORTUÁRIAS."
      ]
    }
  ]
}