{
  "treinamento": "MANUTENÇÃO PREVENTIVA E CORRETIVA EM SISTEMAS DE CLIMATIZAÇÃO - MÓDULO 5_ENGENHARIA",
  "id": 1619,
  "idChecklist": 1322,
  "perguntas": [
    {
      "pergunta": "5) EM UM COMPRESSOR 380V, QUAL É A FAIXA DE TENSÃO PERMITIDA PARA ALIMENTAÇÃO?",
      "opcoes": [
        "ENTRE 320V E 400V.",
        "ENTRE 350V E 410V.",
        "ENTRE 342V E 418V.",
        "ENTRE 360V E 430V."
      ]
    },
    {
      "pergunta": "4) QUAL A FUNÇÃO DO TESTE DE CONTINUIDADE DAS BOBINAS DO COMPRESSOR?",
      "opcoes": [
        "VERIFICAR SE HÁ PASSAGEM DE CORRENTE ENTRE OS TERMINAIS.",
        "CHECAR O NÍVEL DE ÓLEO DO COMPRESSOR.",
        "MEDIR A TEMPERATURA INTERNA DAS BOBINAS.",
        "CONFIRMAR A PRESSÃO INTERNA DO SISTEMA."
      ]
    },
    {
      "pergunta": "3) O QUE INDICA UM APITO NO MULTÍMETRO AO TESTAR A CARCAÇA E OS TERMINAIS DO COMPRESSOR?",
      "opcoes": [
        "QUE HÁ BOA CONTINUIDADE ENTRE AS BOBINAS.",
        "QUE EXISTE FUGA DE CORRENTE E RISCO ELÉTRICO.",
        "QUE O SISTEMA ESTÁ TOTALMENTE SECO.",
        "QUE O CAPACITOR ESTÁ FUNCIONANDO CORRETAMENTE."
      ]
    },
    {
      "pergunta": "2) QUAL É O PRIMEIRO PASSO PARA REALIZAR TESTES NO COMPRESSOR?",
      "opcoes": [
        "DESLIGAR O COMPRESSOR DA REDE ELÉTRICA.",
        "SUBSTITUIR O CAPACITOR.",
        "LIGAR O SISTEMA DE REFRIGERAÇÃO.",
        "CONECTAR A BOMBA DE VÁCUO."
      ]
    },
    {
      "pergunta": "1) O QUE DEVE SER FEITO ANTES DE SUBSTITUIR UM COMPRESSOR DEFEITUOSO?",
      "opcoes": [
        "LIGAR O EQUIPAMENTO PARA VERIFICAR SUPERAQUECIMENTO.",
        "VERIFICAR O HISTÓRICO DO EQUIPAMENTO E GARANTIR QUE O SISTEMA ESTEJA LIMPO E SECO.",
        "INSTALAR O NOVO COMPRESSOR E DEPOIS FAZER O DIAGNÓSTICO.",
        "AUMENTAR A CARGA DE FLUIDO REFRIGERANTE PARA TESTAR O FUNCIONAMENTO."
      ]
    }
  ]
}