{
  "treinamento": "PRISMA - CONSULTA DE RELATÓRIO",
  "id": 1668,
  "idChecklist": 1367,
  "perguntas": [
    {
      "pergunta": "5) QUAL É A PRINCIPAL IMPORTÂNCIA DA FUNCIONALIDADE DE CONSULTA DE RELATÓRIOS?",
      "opcoes": [
        "FACILITAR APENAS O CONTROLE DE PONTO DOS COLABORADORES.",
        "ACOMPANHAR ATIVIDADES, VERIFICAR CONFORMIDADE E APOIAR AUDITORIAS.",
        "DIMINUIR O NÚMERO DE OS'S ABERTAS NO SISTEMA.",
        "PERMITIR APENAS O ACESSO DOS GESTORES AOS DADOS."
      ]
    },
    {
      "pergunta": "4) EM CASO DE DÚVIDAS SOBRE A FUNCIONALIDADE DE CONSULTA DE RELATÓRIO, O QUE O COLABORADOR DEVE FAZER?",
      "opcoes": [
        "IGNORAR E SEGUIR COM O PROCESSO.",
        "CONSULTAR O MANUAL IMPRESSO.",
        "PROCURAR O SUPERVISOR IMEDIATO OU ENTRAR EM CONTATO COM O SUPORTE.",
        "REINICIAR O SISTEMA PRISMA."
      ]
    },
    {
      "pergunta": "3) APÓS ACESSAR O MENU “ORDENS DE SERVIÇO”, O QUE DEVE SER FEITO PARA CONSULTAR UMA OS ESPECÍFICA?",
      "opcoes": [
        "DIGITAR O NOME DO CLIENTE.",
        "CLICAR NA LUPA DO CAMPO DA OS.",
        "SELECIONAR O TIPO DE RELATÓRIO.",
        "ATUALIZAR A PÁGINA."
      ]
    },
    {
      "pergunta": "2) QUAL É O PRIMEIRO PASSO PARA INICIAR A CONSULTA DE RELATÓRIO NO PRISMA?",
      "opcoes": [
        "CLICAR EM “RELATÓRIOS GERENCIAIS”.",
        "ACESSAR O MENU “CONFIGURAÇÕES”.",
        "CLICAR NO MENU “ORDENS DE SERVIÇO”.",
        "SELECIONAR O CAMPO “SUPERVISOR”."
      ]
    },
    {
      "pergunta": "1) QUAL É O OBJETIVO PRINCIPAL DO TREINAMENTO SOBRE CONSULTA DE RELATÓRIO NO SISTEMA PRISMA?",
      "opcoes": [
        "APRENDER A CRIAR RELATÓRIOS PERSONALIZADOS.",
        "CAPACITAR OS COLABORADORES PARA UTILIZAR CORRETAMENTE A FUNCIONALIDADE DE CONSULTA DE RELATÓRIOS.",
        "REALIZAR MANUTENÇÃO NO SISTEMA PRISMA.",
        "GERAR GRÁFICOS ESTATÍSTICOS AUTOMATICAMENTE."
      ]
    }
  ]
}